metacoag/__init__.py
metacoag/cli.py
metacoag/metacoag_runner.py
metacoag/metacoag_utils/__init__.py
metacoag/metacoag_utils/bidirectionalmap.py
metacoag/metacoag_utils/feature_utils.py
metacoag/metacoag_utils/graph_utils.py
metacoag/metacoag_utils/label_prop_utils.py
metacoag/metacoag_utils/marker_gene_utils.py
metacoag/metacoag_utils/matching_utils.py
metacoag/metacoag_utils/auxiliary/marker.hmm
metacoag/metacoag_utils/support/combine_cov.py
metacoag/metacoag_utils/support/gfa2fasta.py
metacoag-1.2.2.dist-info/entry_points.txt
metacoag-1.2.2.dist-info/LICENSE
metacoag-1.2.2.dist-info/WHEEL
metacoag-1.2.2.dist-info/METADATA
metacoag-1.2.2.dist-info/RECORD
