Metadata-Version: 2.1
Name: metacoag
Version: 1.2.2
Summary: MetaCoAG: Binning Metagenomic Contigs via Composition, Coverage and Assembly Graphs
Keywords: metagenomics,binning,contigs,bioinformatics
Author-email: Vijini Mallawaarachchi <viji.mallawaarachchi@gmail.com>
Requires-Python: >=3.9,<3.13
Classifier: Development Status :: 5 - Production/Stable
Classifier: Programming Language :: Python :: 3
Classifier: License :: OSI Approved :: GNU General Public License v3 (GPLv3)
Classifier: Natural Language :: English
Classifier: Topic :: Scientific/Engineering :: Bio-Informatics
Classifier: Operating System :: MacOS
Classifier: Operating System :: POSIX
Requires-Dist: biopython
Requires-Dist: igraph
Requires-Dist: networkx
Requires-Dist: scipy
Requires-Dist: numpy
Requires-Dist: tqdm
Requires-Dist: pandas
Requires-Dist: click
Requires-Dist: black ; extra == "dev"
Requires-Dist: click ; extra == "dev"
Requires-Dist: docformatter ; extra == "dev"
Requires-Dist: flit ; extra == "dev"
Requires-Dist: nox ; extra == "dev"
Requires-Dist: isort ; extra == "dev"
Requires-Dist: pytest ; extra == "dev"
Requires-Dist: pytest-cov ; extra == "dev"
Requires-Dist: pytest-xdist ; extra == "dev"
Requires-Dist: nox ; extra == "test"
Requires-Dist: pytest ; extra == "test"
Requires-Dist: pytest-cov ; extra == "test"
Requires-Dist: pytest-xdist ; extra == "test"
Project-URL: Home, https://metacoag.readthedocs.io
Provides-Extra: dev
Provides-Extra: test
